{"packages/cupertino_icons/assets/CupertinoIcons.ttf":["packages/cupertino_icons/assets/CupertinoIcons.ttf"],"assets/fonts/DIN%20Alternate%20Bold.ttf":["assets/fonts/DIN%20Alternate%20Bold.ttf"],"assets/images/group-10.png":["assets/images/group-10.png","assets/images/2.0x/group-10.png","assets/images/3.0x/group-10.png"],"assets/images/group-6.png":["assets/images/group-6.png","assets/images/2.0x/group-6.png","assets/images/3.0x/group-6.png"],"assets/images/group-9.png":["assets/images/group-9.png","assets/images/2.0x/group-9.png","assets/images/3.0x/group-9.png"],"assets/images/rectangle-2.png":["assets/images/rectangle-2.png","assets/images/2.0x/rectangle-2.png","assets/images/3.0x/rectangle-2.png"]}